sphinx_execute_code/__init__.py
sphinx_execute_code_python3-0.3.dist-info/AUTHORS
sphinx_execute_code_python3-0.3.dist-info/LICENSE.txt
sphinx_execute_code_python3-0.3.dist-info/METADATA
sphinx_execute_code_python3-0.3.dist-info/WHEEL
sphinx_execute_code_python3-0.3.dist-info/top_level.txt
sphinx_execute_code_python3-0.3.dist-info/RECORD
