Metadata-Version: 2.1
Name: sphinx-execute-code-python3
Version: 0.3
Summary: Sphinx support for execution of python code from code blocks or files
Home-page: https://github.com/GrandMoff100/sphinx-execute-code
Author: JP Senior
Author-email: jp.senior@gmail.com
Maintainer: GrandMoff100
Maintainer-email: nlarsen23.student@gmail.com
License: MIT
Keywords: sphinx extension directive execute code
Platform: any
Classifier: Development Status :: 3 - Alpha
Classifier: Intended Audience :: Developers
Classifier: Framework :: Sphinx :: Extension
Classifier: License :: OSI Approved :: MIT License
Classifier: Natural Language :: English
Classifier: Programming Language :: Python :: 2.7
Classifier: Programming Language :: Python :: 3
License-File: LICENSE.txt
License-File: AUTHORS
Requires-Dist: docutils
Requires-Dist: sphinx
